odoo/addons/product_multi_image/README.rst
odoo/addons/product_multi_image/__init__.py
odoo/addons/product_multi_image/__manifest__.py
odoo/addons/product_multi_image/hooks.py
odoo/addons/product_multi_image/i18n/es.po
odoo/addons/product_multi_image/i18n/it.po
odoo/addons/product_multi_image/i18n/product_multi_image.pot
odoo/addons/product_multi_image/images/db.png
odoo/addons/product_multi_image/images/file.png
odoo/addons/product_multi_image/images/product.png
odoo/addons/product_multi_image/images/url.png
odoo/addons/product_multi_image/models/__init__.py
odoo/addons/product_multi_image/models/image.py
odoo/addons/product_multi_image/models/product_product.py
odoo/addons/product_multi_image/models/product_template.py
odoo/addons/product_multi_image/readme/CONFIGURE.rst
odoo/addons/product_multi_image/readme/CONTRIBUTORS.rst
odoo/addons/product_multi_image/readme/CREDITS.rst
odoo/addons/product_multi_image/readme/DESCRIPTION.rst
odoo/addons/product_multi_image/readme/INSTALL.rst
odoo/addons/product_multi_image/readme/ROADMAP.rst
odoo/addons/product_multi_image/static/description/icon.png
odoo/addons/product_multi_image/static/description/icon.svg
odoo/addons/product_multi_image/static/description/index.html
odoo/addons/product_multi_image/tests/__init__.py
odoo/addons/product_multi_image/tests/test_product_multi_image.py
odoo/addons/product_multi_image/views/image_view.xml
odoo/addons/product_multi_image/views/product_template_view.xml
odoo_addon_product_multi_image-15.0.1.0.0.8.dist-info/METADATA
odoo_addon_product_multi_image-15.0.1.0.0.8.dist-info/WHEEL
odoo_addon_product_multi_image-15.0.1.0.0.8.dist-info/top_level.txt
odoo_addon_product_multi_image-15.0.1.0.0.8.dist-info/RECORD
