Metadata-Version: 2.1
Name: odoo-addon-product_multi_image
Version: 15.0.1.0.0.8
Summary: Multiple Images in Products
Home-page: https://github.com/OCA/product-attribute
Author: Antiun Ingeniería, Tecnativa, LasLabs, Odoo Community Association (OCA)
Author-email: support@odoo-community.org
License: AGPL-3
Classifier: Programming Language :: Python
Classifier: Framework :: Odoo
Classifier: Framework :: Odoo :: 15.0
Classifier: License :: OSI Approved :: GNU Affero General Public License v3
Requires-Python: >=3.8
Requires-Dist: odoo-addon-base-multi-image<15.1dev,>=15.0dev
Requires-Dist: odoo<15.1dev,>=15.0a
